brute_force_cython_ext.cpython-311-x86_64-linux-gnu.so
imagededup/__init__.py
imagededup/evaluation/evaluation.py
imagededup/evaluation/__init__.py
imagededup/utils/image_utils.py
imagededup/utils/plotter.py
imagededup/utils/logger.py
imagededup/utils/models.py
imagededup/utils/general_utils.py
imagededup/utils/__init__.py
imagededup/utils/data_generator.py
imagededup/handlers/__init__.py
imagededup/handlers/metrics/information_retrieval.py
imagededup/handlers/metrics/__init__.py
imagededup/handlers/metrics/classification.py
imagededup/handlers/search/brute_force_cython.py
imagededup/handlers/search/brute_force.py
imagededup/handlers/search/__init__.py
imagededup/handlers/search/bktree.py
imagededup/handlers/search/retrieval.py
imagededup/methods/hashing.py
imagededup/methods/__init__.py
imagededup/methods/cnn.py
imagededup_gml-0.3.2.dist-info/LICENSE
imagededup_gml-0.3.2.dist-info/RECORD
imagededup_gml-0.3.2.dist-info/METADATA
imagededup_gml-0.3.2.dist-info/WHEEL
imagededup_gml-0.3.2.dist-info/top_level.txt
