Metadata-Version: 2.2
Name: imagededup-gml
Version: 0.3.2
Summary: Package for image deduplication
Author: Tanuj Jain, Christopher Lennan, Zubin John, Dat Tran
Author-email: tanuj.jain.10@gmail.com, christopherlennan@gmail.com, zrjohn@yahoo.com, datitran@gmail.com
Maintainer-email: build@gimletlabs.ai
License: Apache 2.0
Classifier: Development Status :: 5 - Production/Stable
Classifier: Intended Audience :: Developers
Classifier: Intended Audience :: Science/Research
Classifier: License :: OSI Approved :: Apache Software License
Classifier: Operating System :: POSIX :: Linux
Classifier: Operating System :: MacOS :: MacOS X
Classifier: Operating System :: Microsoft :: Windows
Classifier: Programming Language :: Cython
Classifier: Programming Language :: Python :: 3
Classifier: Programming Language :: Python :: 3.8
Classifier: Programming Language :: Python :: 3.9
Classifier: Programming Language :: Python :: 3.10
Classifier: Topic :: Software Development :: Libraries
Classifier: Topic :: Software Development :: Libraries :: Python Modules
License-File: LICENSE
Requires-Dist: torch
Requires-Dist: torchvision
Requires-Dist: Pillow>=9.0
Requires-Dist: tqdm
Requires-Dist: scikit-learn
Requires-Dist: PyWavelets
Requires-Dist: matplotlib
Provides-Extra: tests
Requires-Dist: pytest; extra == "tests"
Requires-Dist: pytest-cov; extra == "tests"
Requires-Dist: pytest-mock; extra == "tests"
Requires-Dist: codecov; extra == "tests"
Provides-Extra: docs
Requires-Dist: mkdocs; extra == "docs"
Requires-Dist: mkdocs-material; extra == "docs"
Provides-Extra: dev
Requires-Dist: bumpversion; extra == "dev"
Requires-Dist: twine; extra == "dev"
Dynamic: author
Dynamic: author-email
Dynamic: classifier
Dynamic: description
Dynamic: license
Dynamic: maintainer-email
Dynamic: provides-extra
Dynamic: requires-dist
Dynamic: summary
